untool/__init__.py
untool/_version.py
untool/enginellm.py
untool/engineov.py
untool/llmbasemodel.py
untool/llmbasepipeline.py
untool/bindings/__init__.py
untool/bindings/help.py
untool/bindings/template.py
untool/bindings/wrapper.py
untool/libs/aarch64/pcie/libuntool.so
untool/libs/aarch64/soc/libuntool.so
untool/libs/x86_64/pcie/libuntool.so
untool-0.2.2.dist-info/METADATA
untool-0.2.2.dist-info/WHEEL
untool-0.2.2.dist-info/entry_points.txt
untool-0.2.2.dist-info/top_level.txt
untool-0.2.2.dist-info/RECORD
