Metadata-Version: 2.4
Name: untool
Version: 0.2.2
Summary: Union Tool for inference on Sophgo chips
Author-email: wlc952 <wlc952@zju.edu.cn>
License: MIT
Project-URL: Homepage, https://github.com/wlc952/untool-python
Classifier: Programming Language :: Python :: 3
Classifier: License :: OSI Approved :: MIT License
Classifier: Operating System :: POSIX :: Linux
Classifier: Development Status :: 4 - Beta
Classifier: Intended Audience :: Developers
Classifier: Topic :: Scientific/Engineering :: Artificial Intelligence
Requires-Python: >=3.8
Requires-Dist: numpy
Requires-Dist: transformers
Requires-Dist: sentencepiece
Requires-Dist: torch
Requires-Dist: torchvision
Requires-Dist: pillow
